dlog/__init__.py
dlog/decorator.py
dlog/demo_test.py
dlog/logger.py
dlog/conf/__init__.py
dlog/conf/split_by_maxBytes.py
dlog/conf/split_by_time.py
dlog/handles/__init__.py
dlog/handles/split_by_maxBytes.py
dlog/handles/split_by_time.py
dlog-1.0.5.dist-info/METADATA
dlog-1.0.5.dist-info/WHEEL
dlog-1.0.5.dist-info/top_level.txt
dlog-1.0.5.dist-info/RECORD
