Metadata-Version: 2.1
Name: dlog
Version: 1.0.5
Summary: Easy log
Home-page: UNKNOWN
Author: Caturbhuja
Author-email: caturbhuja@foxmail.com
License: MIT
Platform: UNKNOWN
Requires-Dist: concurrent-log-handler (==0.9.19)
Requires-Dist: portalocker (==2.0.0)
